jupyter_resource_usage/__init__.py
jupyter_resource_usage/_version.py
jupyter_resource_usage/api.py
jupyter_resource_usage/config.py
jupyter_resource_usage/metrics.py
jupyter_resource_usage/prometheus.py
jupyter_resource_usage/server_extension.py
jupyter_resource_usage/utils.py
jupyter_resource_usage/static/main.js
jupyter_resource_usage/tests/__init__.py
jupyter_resource_usage/tests/test_basic.py
jupyter_resource_usage-1.2.0.data/data/etc/jupyter/jupyter_notebook_config.d/jupyter_resource_usage.json
jupyter_resource_usage-1.2.0.data/data/etc/jupyter/jupyter_server_config.d/jupyter_resource_usage.json
jupyter_resource_usage-1.2.0.data/data/etc/jupyter/nbconfig/notebook.d/jupyter_resource_usage.json
jupyter_resource_usage-1.2.0.data/data/share/jupyter/nbextensions/jupyter_resource_usage/main.js
jupyter_resource_usage-1.2.0.data/data/share/jupyter/labextensions/@jupyter-server/resource-usage/package.json
jupyter_resource_usage-1.2.0.data/data/share/jupyter/labextensions/@jupyter-server/resource-usage/schemas/@jupyter-server/resource-usage/package.json.orig
jupyter_resource_usage-1.2.0.data/data/share/jupyter/labextensions/@jupyter-server/resource-usage/schemas/@jupyter-server/resource-usage/topbar-item.json
jupyter_resource_usage-1.2.0.data/data/share/jupyter/labextensions/@jupyter-server/resource-usage/static/114.8d6e04d9186cda5f713e.js
jupyter_resource_usage-1.2.0.data/data/share/jupyter/labextensions/@jupyter-server/resource-usage/static/311.dc54ab57a76db15e51e8.js
jupyter_resource_usage-1.2.0.data/data/share/jupyter/labextensions/@jupyter-server/resource-usage/static/489.6aed0d21583f7c0f3cea.js
jupyter_resource_usage-1.2.0.data/data/share/jupyter/labextensions/@jupyter-server/resource-usage/static/643.00ea3bded09f7fdc4270.js
jupyter_resource_usage-1.2.0.data/data/share/jupyter/labextensions/@jupyter-server/resource-usage/static/remoteEntry.09935b5f2738ef3c32f2.js
jupyter_resource_usage-1.2.0.dist-info/METADATA
jupyter_resource_usage-1.2.0.dist-info/WHEEL
jupyter_resource_usage-1.2.0.dist-info/licenses/LICENSE
jupyter_resource_usage-1.2.0.dist-info/RECORD
