Metadata-Version: 2.4
Name: jupyter-resource-usage
Version: 1.2.0
Summary: Jupyter Extension to show resource usage
Project-URL: Homepage, https://github.com/jupyter-server/jupyter-resource-usage
Author: Jupyter Development Team
License: Copyright (c) 2016, Yuvi Panda
License-File: LICENSE
Keywords: IPython,Jupyter,JupyterLab
Classifier: Framework :: Jupyter
Classifier: Framework :: Jupyter :: JupyterLab
Classifier: Framework :: Jupyter :: JupyterLab :: 4
Classifier: Framework :: Jupyter :: JupyterLab :: Extensions
Classifier: Framework :: Jupyter :: JupyterLab :: Extensions :: Prebuilt
Classifier: Intended Audience :: Developers
Classifier: Intended Audience :: Science/Research
Classifier: License :: OSI Approved :: BSD License
Classifier: Programming Language :: Python
Classifier: Programming Language :: Python :: 3
Classifier: Programming Language :: Python :: 3.9
Classifier: Programming Language :: Python :: 3.10
Classifier: Programming Language :: Python :: 3.11
Classifier: Programming Language :: Python :: 3.12
Classifier: Programming Language :: Python :: 3.13
Requires-Python: >=3.9
Requires-Dist: jupyter-server>=2.0
Requires-Dist: prometheus-client
Requires-Dist: psutil>=5.6
Requires-Dist: pyzmq>=19
Provides-Extra: dev
Requires-Dist: autopep8; extra == 'dev'
Requires-Dist: black; extra == 'dev'
Requires-Dist: flake8; extra == 'dev'
Requires-Dist: mock; extra == 'dev'
Requires-Dist: pytest; extra == 'dev'
Requires-Dist: pytest-cov>=2.6.1; extra == 'dev'
